llf_package
